dmm/daemons/__init__.py
dmm/daemons/core.py
dmm/daemons/fts.py
dmm/daemons/rucio.py
dmm/daemons/sense.py
dmm/daemons/sites.py
dmm/db/__init__.py
dmm/db/models.py
dmm/db/session.py
dmm/frontend/__init__.py
dmm/frontend/frontend.py
dmm/frontend/templates/index.html
dmm/main/__init__.py
dmm/main/dmm.py
dmm/main/orchestrator.py
dmm/utils/__init__.py
dmm/utils/config.py
dmm/utils/db.py
dmm/utils/fts.py
dmm/utils/monit.py
dmm/utils/sense.py
dmm/utils/siterm.py
sense_dmm-0.3.0.dist-info/LICENSE
sense_dmm-0.3.0.dist-info/METADATA
sense_dmm-0.3.0.dist-info/WHEEL
sense_dmm-0.3.0.dist-info/entry_points.txt
sense_dmm-0.3.0.dist-info/top_level.txt
sense_dmm-0.3.0.dist-info/RECORD
