Metadata-Version: 2.1
Name: sense-dmm
Version: 0.3.0
Summary: Data Movement Manager for Rucio SENSE interoperatio prototype
Author-email: Aashay Arora <aaarora@ucsd.edu>
Project-URL: Homepage, https://github.com/aashayarora/rucio-sense-dmm
Project-URL: Issues, https://github.com/aashayarora/rucio-sense-dmm/issues
Classifier: Programming Language :: Python :: 3
Classifier: License :: OSI Approved :: MIT License
Classifier: Operating System :: OS Independent
Requires-Python: >=3.7
License-File: LICENSE
Requires-Dist: sense-o-api ==1.31
Requires-Dist: sqlalchemy
Requires-Dist: psycopg2-binary
Requires-Dist: networkx
Requires-Dist: rucio-clients
Requires-Dist: flask
Requires-Dist: waitress
